CHANGES
LICENSE
MANIFEST.in
README.rst
requirements.txt
setup.py
dopy/__init__.py
dopy/manager.py
dopy.egg-info/PKG-INFO
dopy.egg-info/SOURCES.txt
dopy.egg-info/dependency_links.txt
dopy.egg-info/pbr.json
dopy.egg-info/requires.txt
dopy.egg-info/top_level.txt