Metadata-Version: 1.1
Name: dopy
Version: 0.3.3
Summary: Python client for the Digital Ocean API
Home-page: https://github.com/devo-ps/dopy
Author: Vincent Viallet
Author-email: vincent@devo.ps
License: The MIT License (MIT)
